peyton/__init__.py
peyton/competition.py
peyton/silly.py
peyton/throne.py
peyton/user.py
peyton/stats/__init__.py
peyton/stats/dixoncoles.py
peyton-0.2.0.dist-info/DESCRIPTION.rst
peyton-0.2.0.dist-info/LICENSE.txt
peyton-0.2.0.dist-info/METADATA
peyton-0.2.0.dist-info/RECORD
peyton-0.2.0.dist-info/WHEEL
peyton-0.2.0.dist-info/metadata.json
peyton-0.2.0.dist-info/top_level.txt
