Metadata-Version: 2.0
Name: peyton
Version: 0.2.0
Summary: Peyton, an API wrapper for the Throne.AI Platform
Home-page: https://throne.ai/
Author: Ross Taylor
Author-email: rj-taylor@live.co.uk
License: MIT
Keywords: throne api wrapper
Platform: UNKNOWN
Classifier: Development Status :: 5 - Production/Stable
Classifier: Environment :: Console
Classifier: Intended Audience :: Developers
Classifier: License :: OSI Approved :: BSD License
Classifier: Natural Language :: English
Classifier: Operating System :: OS Independent
Classifier: Programming Language :: Python
Classifier: Programming Language :: Python :: 3.5
Classifier: Programming Language :: Python :: 3.6
Classifier: Programming Language :: Python :: Implementation :: CPython
Classifier: Topic :: Utilities
